amaproductreviews.py
amaproductreviews-0.0.7.dist-info/METADATA
amaproductreviews-0.0.7.dist-info/WHEEL
amaproductreviews-0.0.7.dist-info/RECORD
