Metadata-Version: 2.1
Name: AmaProductReviews
Version: 0.0.7
Summary: Analyze Amazon product reviews
Author: olamine zakaria
Author-email: olaminezakaria03@gmail.com
Requires-Python: >=3.8,<4.0
Classifier: Programming Language :: Python :: 3
Classifier: Programming Language :: Python :: 3.8
Classifier: Programming Language :: Python :: 3.9
Classifier: Programming Language :: Python :: 3.10
Classifier: Programming Language :: Python :: 3.11
Classifier: Programming Language :: Python :: 3.12
Requires-Dist: beautifulsoup4
Requires-Dist: requests (>=2.31.0,<3.0.0)
Requires-Dist: selenium
Requires-Dist: webdriver_manager
